srilanka/__init__.py
srilanka/data.py
srilanka/data2.py
srilanka-1.0.1.dist-info/LICENSE
srilanka-1.0.1.dist-info/METADATA
srilanka-1.0.1.dist-info/WHEEL
srilanka-1.0.1.dist-info/top_level.txt
srilanka-1.0.1.dist-info/RECORD
