Metadata-Version: 2.2
Name: srilanka
Version: 1.0.1
Summary: A comprehensive package for working with data about Sri Lanka, including provinces, districts, and cities.
Home-page: https://github.com/ishanoshada/Srilanka
Author: Ishan Oshada
Author-email: ishan.kodithuwakku.offical@gmail.com
Project-URL: Documentation, https://github.com/ishanoshada/Srilanka#readme
Project-URL: Source, https://github.com/ishanoshada/Srilanka
Project-URL: Tracker, https://github.com/ishanoshada/Srilanka/issues
Keywords: Sri Lanka,provinces,districts,cities,data,utility
Classifier: Development Status :: 4 - Beta
Classifier: Intended Audience :: Developers
Classifier: License :: OSI Approved :: MIT License
Classifier: Programming Language :: Python :: 3
Classifier: Programming Language :: Python :: 3.6
Classifier: Programming Language :: Python :: 3.7
Classifier: Programming Language :: Python :: 3.8
Classifier: Programming Language :: Python :: 3.9
Classifier: Topic :: Software Development :: Libraries :: Python Modules
Classifier: Topic :: Software Development :: Libraries :: Application Frameworks
Classifier: Natural Language :: English
Requires-Python: >=3.6
License-File: LICENSE
Dynamic: author
Dynamic: author-email
Dynamic: classifier
Dynamic: description
Dynamic: description-content-type
Dynamic: home-page
Dynamic: keywords
Dynamic: project-url
Dynamic: requires-python
Dynamic: summary
